em/__init__.py
em/api.py
em/basecrawler.py
em/errors.py
em/portfolio.py
em/position.py
em/quotation.py
em/selectors.py
em/server.py
em/util.py
zillionare_em-0.1.1.dist-info/LICENSE
zillionare_em-0.1.1.dist-info/WHEEL
zillionare_em-0.1.1.dist-info/METADATA
zillionare_em-0.1.1.dist-info/RECORD
