Metadata-Version: 2.1
Name: zillionare-em
Version: 0.1.1
Summary: earn money.
Home-page: https://github.com/zillionare/em
License: MIT
Author: Aaron Yang
Author-email: code@jieyu.ai
Requires-Python: >=3.7,<4.0
Classifier: Development Status :: 2 - Pre-Alpha
Classifier: Intended Audience :: Developers
Classifier: License :: OSI Approved :: MIT License
Classifier: Natural Language :: English
Classifier: Programming Language :: Python :: 3
Classifier: Programming Language :: Python :: 3.7
Classifier: Programming Language :: Python :: 3.8
Classifier: Programming Language :: Python :: 3.9
Provides-Extra: dev
Provides-Extra: doc
Provides-Extra: test
Requires-Dist: aiofiles (>=0.7.0,<0.8.0)
Requires-Dist: aiohttp (>=3.7.4,<4.0.0)
Requires-Dist: arrow (>=1.1.1,<2.0.0)
Requires-Dist: black (==20.8b1); extra == "test"
Requires-Dist: fire (==0.4.0)
Requires-Dist: flake8 (==3.8.4); extra == "test"
Requires-Dist: flake8-docstrings (>=1.6.0,<2.0.0); extra == "test"
Requires-Dist: hacktcha (==0.2.2)
Requires-Dist: isort (==5.6.4); extra == "test"
Requires-Dist: mkdocs (>=1.1.2,<2.0.0); extra == "doc"
Requires-Dist: mkdocs-autorefs (==0.1.1); extra == "doc"
Requires-Dist: mkdocs-include-markdown-plugin (>=1.0.0,<2.0.0); extra == "doc"
Requires-Dist: mkdocs-material (>=6.1.7,<7.0.0); extra == "doc"
Requires-Dist: mkdocs-material-extensions (>=1.0.1,<2.0.0)
Requires-Dist: mkdocstrings (>=0.13.6,<0.14.0); extra == "doc"
Requires-Dist: pillow (>=8.2,<9.0)
Requires-Dist: pip (>=20.3.1,<21.0.0); extra == "dev"
Requires-Dist: pre-commit (>=2.12.0,<3.0.0); extra == "dev"
Requires-Dist: pyee (>=7.0.4,<8.0.0)
Requires-Dist: pyppeteer (>=0.2.2,<0.3.0)
Requires-Dist: pytest (==6.2.4); extra == "test"
Requires-Dist: pytest-cov (==2.10.1); extra == "test"
Requires-Dist: sanic (>=21.3.4,<22.0.0)
Requires-Dist: toml (>=0.10.2,<0.11.0); extra == "dev"
Requires-Dist: tox (>=3.20.1,<4.0.0); extra == "dev"
Requires-Dist: twine (>=3.3.0,<4.0.0); extra == "dev"
Requires-Dist: virtualenv (>=20.2.2,<21.0.0); extra == "dev"
Requires-Dist: websockets (>=8.1.0,<9.0.0)
